pycontests/__init__.py
pycontests-0.1.0.dist-info/LICENSE
pycontests-0.1.0.dist-info/METADATA
pycontests-0.1.0.dist-info/WHEEL
pycontests-0.1.0.dist-info/top_level.txt
pycontests-0.1.0.dist-info/RECORD
